{
  "Nom Societe": "GRADIAnt",
  "info payment": {
    "Nom du Client": "Veepee TLS",
    "Adresse Client": "13 avenue des champs-élysées, 91888 Paris, France",
    "Numéro Facture": "FAC2025010137",
    "Date Facturation": "12/06/2025",
    "Date Echeance": "20/06/2025",
    "Type d'opération": "Conseil en stratégie data",
    "Total TTC": 13828.68
  },
  "table": [
    {
      "Description": "Cloud Migration",
      "Date": "13/06/2025",
      "TVA": 20,
      "Montant HT": 3459.78,
      "Total TTC": 4151.74
    },
    {
      "Description": "Cloud Migration",
      "Date": "14/06/2025",
      "TVA": 20,
      "Montant HT": 1080.34,
      "Total TTC": 1296.41
    },
    {
      "Description": "Sécurité et conformité des données",
      "Date": "15/06/2025",
      "TVA": 20,
      "Montant HT": 3727.39,
      "Total TTC": 4472.87
    },
    {
      "Description": "Sécurité et conformité des données",
      "Date": "16/06/2025",
      "TVA": 20,
      "Montant HT": 3256.38,
      "Total TTC": 3907.66
    }
  ]
}